{"lda_shuju": [{"yuqing_wenzibintu": [{"name": "\u5c45\u6c11\u5b89\u7f6e", "value": 156}, {"name": "\u5de5\u4f5c", "value": 122}, {"name": "\u5de5\u7a0b\u5f71\u54cd", "value": 116}, {"name": "\u62c6\u8fc1", "value": 150}, {"name": "\u7269\u4e1a", "value": 98}]}, {"yuqingzoushi": [{"xAxis": ["2018-01", "2018-02", "2018-03", "2018-04", "2018-05", "2018-06", "2018-07", "2018-08", "2018-09", "2018-10", "2018-11", "2018-12"]}, {"series": [{"name": "\u5c45\u6c11\u5b89\u7f6e", "data": [34.0, 12.0, 21.0, 4.0, 4.0, 8.0, 20.0, 22.0, 15.0, 8.0, 7.0, 1.0]}, {"name": "\u5de5\u4f5c", "data": [20.0, 12.0, 19.0, 5.0, 7.0, 7.0, 6.0, 12.0, 16.0, 10.0, 8.0, 0.0]}, {"name": "\u5de5\u7a0b\u5f71\u54cd", "data": [16.0, 14.0, 17.0, 1.0, 5.0, 9.0, 6.0, 25.0, 10.0, 6.0, 4.0, 3.0]}, {"name": "\u62c6\u8fc1", "data": [10.0, 14.0, 18.0, 7.0, 0.0, 12.0, 13.0, 21.0, 19.0, 14.0, 12.0, 10.0]}, {"name": "\u7269\u4e1a", "data": [11.0, 17.0, 9.0, 2.0, 4.0, 4.0, 12.0, 8.0, 10.0, 12.0, 6.0, 3.0]}]}]}]}